{
  "id": "node_modules/is-glob/README",
  "title": "is-glob [![NPM version](https://img.shields.io/npm/v/is-glob.svg?style=flat)](https://www.npmjs.com/package/is-glob) [![NPM monthly downloads](https://img.shields.io/npm/dm/is-glob.svg?style=flat)](https://npmjs.org/package/is-glob) [![NPM total downloads](https://img.shields.io/npm/dt/is-glob.svg?style=flat)](https://npmjs.org/package/is-glob) [![Build Status](https://img.shields.io/github/workflow/status/micromatch/is-glob/dev)](https://github.com/micromatch/is-glob/actions)",
  "description": "Returns true if the given string looks like a glob pattern or an extglob pattern. This makes it easy to create code that only uses external modules like node-glob when necessary, resulting in much faster code execution and initialization time, and a better user experience.",
  "source": "@site/node_modules/is-glob/README.md",
  "sourceDirName": "node_modules/is-glob",
  "slug": "/node_modules/is-glob/",
  "permalink": "/Clear-AI/node_modules/is-glob/",
  "draft": false,
  "unlisted": false,
  "editUrl": "https://github.com/wsyeabsera/Clear-AI/tree/main/research/docs/node_modules/is-glob/README.md",
  "tags": [],
  "version": "current",
  "frontMatter": {}
}