{
  "id": "node_modules/@babel/compat-data/README",
  "title": "@babel/compat-data",
  "description": "The compat-data to determine required Babel plugins",
  "source": "@site/node_modules/@babel/compat-data/README.md",
  "sourceDirName": "node_modules/@babel/compat-data",
  "slug": "/node_modules/@babel/compat-data/",
  "permalink": "/Clear-AI/node_modules/@babel/compat-data/",
  "draft": false,
  "unlisted": false,
  "editUrl": "https://github.com/wsyeabsera/Clear-AI/tree/main/research/docs/node_modules/@babel/compat-data/README.md",
  "tags": [],
  "version": "current",
  "frontMatter": {}
}