{
  "id": "node_modules/proto-list/README",
  "title": "README",
  "description": "A list of objects, bound by their prototype chain.",
  "source": "@site/node_modules/proto-list/README.md",
  "sourceDirName": "node_modules/proto-list",
  "slug": "/node_modules/proto-list/",
  "permalink": "/Clear-AI/node_modules/proto-list/",
  "draft": false,
  "unlisted": false,
  "editUrl": "https://github.com/wsyeabsera/Clear-AI/tree/main/research/docs/node_modules/proto-list/README.md",
  "tags": [],
  "version": "current",
  "frontMatter": {}
}