{
  "id": "node_modules/is-stream/readme",
  "title": "is-stream",
  "description": "Check if something is a Node.js stream",
  "source": "@site/node_modules/is-stream/readme.md",
  "sourceDirName": "node_modules/is-stream",
  "slug": "/node_modules/is-stream/",
  "permalink": "/Clear-AI/node_modules/is-stream/",
  "draft": false,
  "unlisted": false,
  "editUrl": "https://github.com/wsyeabsera/Clear-AI/tree/main/research/docs/node_modules/is-stream/readme.md",
  "tags": [],
  "version": "current",
  "frontMatter": {}
}