{
  "id": "packages/client",
  "title": "🧠 Client Package - Intelligent AI Client",
  "description": "The Clear AI client is a modern React application that provides the intelligent user interface for interacting with the AI-powered tool execution system. Built with TypeScript, Vite, and Tailwind CSS, it offers advanced intelligence features, memory visualization, and sophisticated relationship analysis with 8.5/10 intelligence score.",
  "source": "@site/docs/packages/client.md",
  "sourceDirName": "packages",
  "slug": "/packages/client",
  "permalink": "/clear-ai/docs/packages/client",
  "draft": false,
  "unlisted": false,
  "editUrl": "https://github.com/wsyeabsera/clear-ai/tree/main/research/docs/docs/packages/client.md",
  "tags": [],
  "version": "current",
  "frontMatter": {},
  "sidebar": "tutorialSidebar",
  "previous": {
    "title": "Intelligence Assessment",
    "permalink": "/clear-ai/docs/agent-intelligence"
  },
  "next": {
    "title": "🧠 Server Package - Intelligent AI Server",
    "permalink": "/clear-ai/docs/packages/server"
  }
}